gurobipy/__init__.py
gurobipy/__init__.pyi
gurobipy/_attrconst.py
gurobipy/_attrutil.cp312-win_amd64.pyd
gurobipy/_batch.cp312-win_amd64.pyd
gurobipy/_callbackconst.py
gurobipy/_core.cp312-win_amd64.pyd
gurobipy/_errorconst.py
gurobipy/_exception.cp312-win_amd64.pyd
gurobipy/_grb.py
gurobipy/_helpers.cp312-win_amd64.pyd
gurobipy/_load_model.py
gurobipy/_lowlevel.cp312-win_amd64.pyd
gurobipy/_matrixapi.cp312-win_amd64.pyd
gurobipy/_model.cp312-win_amd64.pyd
gurobipy/_modelutil.cp312-win_amd64.pyd
gurobipy/_paramconst.py
gurobipy/_paramdetails.py
gurobipy/_statusconst.py
gurobipy/_util.cp312-win_amd64.pyd
gurobipy/gurobi.lic
gurobipy/gurobi130.dll
gurobipy/nlfunc.py
gurobipy/nlfunc.pyi
gurobipy/py.typed
gurobipy-13.0.1.dist-info/licenses/LICENSE.txt
gurobipy-13.0.1.dist-info/METADATA
gurobipy-13.0.1.dist-info/WHEEL
gurobipy-13.0.1.dist-info/top_level.txt
gurobipy-13.0.1.dist-info/RECORD
