Metadata-Version: 2.4
Name: gurobipy
Version: 13.0.1
Summary: Python interface to Gurobi
Home-page: https://www.gurobi.com
Author: Gurobi Optimization, LLC
License: Proprietary
Project-URL: Documentation, https://docs.gurobi.com
Keywords: optimization,mip,lp
Platform: Windows
Platform: Linux
Platform: macOS
Classifier: Programming Language :: Python :: 3
Classifier: Programming Language :: Python :: 3.10
Classifier: Programming Language :: Python :: 3.11
Classifier: Programming Language :: Python :: 3.12
Classifier: Programming Language :: Python :: 3.13
Classifier: Programming Language :: Python :: 3.14
Classifier: Operating System :: OS Independent
Classifier: Programming Language :: Python :: Implementation :: CPython
Requires-Python: >=3.10
License-File: LICENSE.txt
Provides-Extra: matrixapi
Requires-Dist: numpy; extra == "matrixapi"
Requires-Dist: scipy; extra == "matrixapi"
Dynamic: author
Dynamic: classifier
Dynamic: description
Dynamic: description-content-type
Dynamic: home-page
Dynamic: keywords
Dynamic: license
Dynamic: license-file
Dynamic: platform
Dynamic: project-url
Dynamic: provides-extra
Dynamic: requires-python
Dynamic: summary
